MANIFEST.in
setup.py
.github/README.md
docs/__init__.py
docs/conf.py
pymerger/__init__.py
pymerger/__main__.py
pymerger/circular_dependencies.py
pymerger/comments.py
pymerger/file_parser.py
pymerger/merger.py
pymerger.egg-info/PKG-INFO
pymerger.egg-info/SOURCES.txt
pymerger.egg-info/dependency_links.txt
pymerger.egg-info/requires.txt
pymerger.egg-info/top_level.txt
test/__init__.py
test/circular_dependencies/__init__.py
test/circular_dependencies/test_.py
test/comments/__init__.py
test/comments/bisection.py
test/comments/bisection_no_comms.py
test/comments/test_.py
test/file_parser/__init__.py
test/file_parser/seeyou.py
test/file_parser/test_.py
test/merger/__init__.py
test/merger/test_.py