Metadata-Version: 2.1
Name: pymerger
Version: 1.0.0
Summary: Python, MicroPython and CircuitPython files merger
Home-page: https://github.com/yamenk-gribaudo/pymerger
Author: yyaammeennkk
Author-email: yyaammeennkk@gmail.com
License: MIT
Keywords: merger files
Platform: UNKNOWN
Classifier: Topic :: Text Processing :: General
Classifier: Development Status :: 3 - Alpha
Classifier: Programming Language :: Python :: 3
Classifier: License :: OSI Approved :: MIT License
Classifier: Operating System :: OS Independent
